hass_pyscript_kernel/__init__.py
hass_pyscript_kernel/__main__.py
hass_pyscript_kernel/install.py
hass_pyscript_kernel/shim.py
hass_pyscript_kernel/version.py
hass_pyscript_kernel/kernel_files/logo-32x32.png
hass_pyscript_kernel/kernel_files/logo-64x64.png
hass_pyscript_kernel/kernel_files/pyscript.conf
hass_pyscript_kernel-1.0.0.dist-info/LICENSE
hass_pyscript_kernel-1.0.0.dist-info/METADATA
hass_pyscript_kernel-1.0.0.dist-info/WHEEL
hass_pyscript_kernel-1.0.0.dist-info/entry_points.txt
hass_pyscript_kernel-1.0.0.dist-info/top_level.txt
hass_pyscript_kernel-1.0.0.dist-info/RECORD
