Metadata-Version: 2.1
Name: hass-pyscript-kernel
Version: 1.0.0
Summary: Home Assistant Pyscript Jupyter kernel shim
Home-page: https://github.com/craigbarratt/hass-pyscript-jupyter
Author: Craig Barratt
Author-email: cbarratt@users.sourceforge.net
License: Apache License 2.0
Download-URL: https://github.com/craigbarratt/hass-pyscript-jupyter/archive/1.0.0.tar.gz
Keywords: hass,home automation,pyscript,jupyter kernel,jupyter,kernel,automation,python,interpreter
Platform: any
Classifier: Development Status :: 4 - Beta
Classifier: Intended Audience :: Developers
Classifier: Operating System :: OS Independent
Classifier: Programming Language :: Python :: 3
Classifier: Programming Language :: Python :: 3.7
Classifier: Programming Language :: Python :: 3.8
Classifier: Topic :: Utilities
Classifier: Topic :: Home Automation
Requires-Python: >=3.7
Requires-Dist: aiohttp
Requires-Dist: aiohttp-socks
Requires-Dist: jupyter-client
Requires-Dist: jupyter-core
